exampe_pip_package/__init__.py
exampe_pip_package-0.0.4.dist-info/LICENSE
exampe_pip_package-0.0.4.dist-info/METADATA
exampe_pip_package-0.0.4.dist-info/WHEEL
exampe_pip_package-0.0.4.dist-info/top_level.txt
exampe_pip_package-0.0.4.dist-info/RECORD
