Metadata-Version: 2.1
Name: exampe-pip-package
Version: 0.0.4
Summary: Just a pip package example
Home-page: https://github.com/XingangShi/exampe_pip_package.git
Author: geekpanshi
Author-email: vincentsxg@gmail.com
License: UNKNOWN
Platform: UNKNOWN
Classifier: Programming Language :: Python :: 3
Classifier: License :: OSI Approved :: MIT License
Classifier: Operating System :: OS Independent
